docums_literate_nav/__init__.py
docums_literate_nav/exceptions.py
docums_literate_nav/parser.py
docums_literate_nav/plugin.py
docums_literate_nav/py.typed
docums_literate_nav-0.6.0.dist-info/METADATA
docums_literate_nav-0.6.0.dist-info/WHEEL
docums_literate_nav-0.6.0.dist-info/entry_points.txt
docums_literate_nav-0.6.0.dist-info/licenses/LICENSE.md
docums_literate_nav-0.6.0.dist-info/RECORD
